Metadata-Version: 2.4
Name: mcp-server-vikingdb-fastmcp
Version: 0.1.3
Summary: a mcp server for vikingdb store and search
Project-URL: Homepage, https://github.com/fastmcp-me/vikingdb-mcp-server#readme
Project-URL: Repository, https://github.com/fastmcp-me/vikingdb-mcp-server.git
Project-URL: Issues, https://github.com/fastmcp-me/vikingdb-mcp-server/issues
Author-email: KashiwaByte <471314513@qq.com>
Requires-Python: >=3.10
Requires-Dist: aiohttp>=3.11.10
Requires-Dist: mcp>=1.1.0
Requires-Dist: python-dotenv>=1.0.1
Requires-Dist: volcengine>=1.0.164
